storage_layout_extractor-0.6.3.dist-info/METADATA
storage_layout_extractor-0.6.3.dist-info/WHEEL
storage_layout_extractor-0.6.3.dist-info/licenses/LICENSE
storage_layout_extractor/__init__.py
storage_layout_extractor/__init__.pyi
storage_layout_extractor/py.typed
storage_layout_extractor/storage_layout_extractor.cpython-310-x86_64-linux-gnu.so
storage_layout_extractor-0.6.3.dist-info/RECORD
