Metadata-Version: 2.4
Name: storage-layout-extractor
Version: 0.6.3
Classifier: Programming Language :: Rust
Classifier: Programming Language :: Python :: Implementation :: CPython
Classifier: Programming Language :: Python :: 3.10
Classifier: Programming Language :: Python :: 3.11
Classifier: Programming Language :: Python :: 3.12
Classifier: Development Status :: 4 - Beta
Classifier: Intended Audience :: Developers
Classifier: Topic :: Software Development :: Disassemblers
Classifier: Topic :: Security
Classifier: License :: OSI Approved :: GNU Affero General Public License v3 or later (AGPLv3+)
License-File: LICENSE
Summary: Python bindings for storage-layout-extractor - EVM bytecode storage layout analysis
Keywords: ethereum,evm,storage,layout,smart-contracts,bytecode,analysis
Home-Page: https://github.com/smlxlio/storage-layout-extractor
Requires-Python: >=3.10
Project-URL: Homepage, https://github.com/jalbrekt85/storage-layout-extractor-py
Project-URL: Repository, https://github.com/jalbrekt85/storage-layout-extractor-py
Project-URL: Issues, https://github.com/jalbrekt85/storage-layout-extractor-py/issues
